alert_thresholds/__init__.py
alert_thresholds/admin.py
alert_thresholds/apps.py
alert_thresholds/choices.py
alert_thresholds/conf.py
alert_thresholds/mixins.py
alert_thresholds/models.py
alert_thresholds/management/__init__.py
alert_thresholds/management/commands/__init__.py
alert_thresholds/management/commands/sync_alert_metrics.py
alert_thresholds/migrations/0001_initial.py
alert_thresholds/migrations/__init__.py
alert_thresholds/templates/admin/alert_thresholds/threshold_change_form.html
django_multi_level_alerts-1.0.1.dist-info/licenses/LICENSE
django_multi_level_alerts-1.0.1.dist-info/METADATA
django_multi_level_alerts-1.0.1.dist-info/WHEEL
django_multi_level_alerts-1.0.1.dist-info/top_level.txt
django_multi_level_alerts-1.0.1.dist-info/RECORD
