Metadata-Version: 2.4
Name: django-multi-level-alerts
Version: 1.0.1
Summary: A reusable Django package for managing multi-level alert thresholds with support for different metrics, operators, and alert levels
Author-email: Mohammad Zarei <mohammad.zarei1380@gmail.com>
License: MIT
Project-URL: Homepage, https://github.com/zarei-dev/django-multi-level-alerts
Project-URL: Bug Tracker, https://github.com/zarei-dev/django-multi-level-alerts/issues
Project-URL: Source, https://github.com/zarei-dev/django-multi-level-alerts
Project-URL: Documentation, https://github.com/zarei-dev/django-multi-level-alerts#readme
Keywords: django,alerts,thresholds,monitoring,notifications,warning,critical,emergency
Classifier: Development Status :: 4 - Beta
Classifier: Environment :: Web Environment
Classifier: Framework :: Django
Classifier: Framework :: Django :: 4.2
Classifier: Framework :: Django :: 5.0
Classifier: Framework :: Django :: 5.1
Classifier: Intended Audience :: Developers
Classifier: License :: OSI Approved :: MIT License
Classifier: Operating System :: OS Independent
Classifier: Programming Language :: Python :: 3
Classifier: Programming Language :: Python :: 3.10
Classifier: Programming Language :: Python :: 3.11
Classifier: Programming Language :: Python :: 3.12
Classifier: Programming Language :: Python :: 3.13
Classifier: Topic :: Software Development :: Libraries :: Python Modules
Classifier: Topic :: System :: Monitoring
Requires-Python: >=3.10
License-File: LICENSE
Requires-Dist: Django>=4.2
Dynamic: license-file
